vamas/__init__.py
vamas/errors.py
vamas/py.typed
vamas/vamas.py
vamas/vamas_block.py
vamas/vamas_header.py
vamas-0.2.0.dist-info/METADATA
vamas-0.2.0.dist-info/WHEEL
vamas-0.2.0.dist-info/licenses/LICENSE
vamas-0.2.0.dist-info/RECORD
