Metadata-Version: 2.4
Name: vamas
Version: 0.2.0
Summary: Python package to read vamas (.vms) files
Project-URL: homepage, https://github.com/matkrin/vamas
Project-URL: documentation, https://matkrin.github.io/vamas
Author-email: Matthias Krinninger <matkrin@protonmail.com>
License: BSD-3-Clause
License-File: LICENSE
Classifier: Development Status :: 3 - Alpha
Classifier: Intended Audience :: Developers
Classifier: Intended Audience :: Science/Research
Classifier: License :: OSI Approved :: BSD License
Classifier: Operating System :: OS Independent
Classifier: Programming Language :: Python :: 3
Classifier: Topic :: Scientific/Engineering
Requires-Python: >=3.8
